CHANGELOG.md
LICENSE
MANIFEST.in
README.rst
setup.cfg
setup.py
django_google_adwords/__init__.py
django_google_adwords/errors.py
django_google_adwords/helper.py
django_google_adwords/lock.py
django_google_adwords/models.py
django_google_adwords/settings.py
django_google_adwords/tasks.py
django_google_adwords.egg-info/PKG-INFO
django_google_adwords.egg-info/SOURCES.txt
django_google_adwords.egg-info/dependency_links.txt
django_google_adwords.egg-info/not-zip-safe
django_google_adwords.egg-info/requires.txt
django_google_adwords.egg-info/top_level.txt
django_google_adwords/management/__init__.py
django_google_adwords/management/commands/__init__.py
django_google_adwords/management/commands/gadapi_test_adwords.py
django_google_adwords/migrations/0001_initial.py
django_google_adwords/migrations/__init__.py
django_google_adwords/south_migrations/0001_initial.py
django_google_adwords/south_migrations/0002_auto__del_field_ad_description_line1__del_field_ad_description_line2__.py
django_google_adwords/south_migrations/0003_auto__add_field_ad_ad_approval_status.py
django_google_adwords/south_migrations/__init__.py
django_google_adwords/tests/__init__.py
django_google_adwords/tests/models.py
requirements/default-django17.txt
requirements/default.txt
requirements/pkgutils.txt
requirements/test.txt
requirements/test3.txt